requests_dump.py
requests_dump2-0.2.dist-info/METADATA
requests_dump2-0.2.dist-info/RECORD
requests_dump2-0.2.dist-info/WHEEL
requests_dump2-0.2.dist-info/top_level.txt
