Metadata-Version: 2.1
Name: requests-dump2
Version: 0.2
Summary: dump requests' requests http message content to stderr or your custom file
Home-page: https://github.com/weaming/requests-dump
Author: weaming
Author-email: garden.yuen@gmail.com
License: UNKNOWN
Project-URL: Source, https://github.com/weaming/requests-dump
Project-URL: Bug Reports, https://github.com/weaming/requests-dump
Keywords: math
Platform: UNKNOWN
Requires-Dist: requests
